odoo/addons/l10n_ru/README.rst
odoo/addons/l10n_ru/__init__.py
odoo/addons/l10n_ru/__manifest__.py
odoo/addons/l10n_ru/data/account_account_tag_data.xml
odoo/addons/l10n_ru/data/template/account.account-ru.csv
odoo/addons/l10n_ru/data/template/account.group-ru.csv
odoo/addons/l10n_ru/data/template/account.tax-ru.csv
odoo/addons/l10n_ru/data/template/account.tax.group-ru.csv
odoo/addons/l10n_ru/i18n/l10n_ru.pot
odoo/addons/l10n_ru/models/__init__.py
odoo/addons/l10n_ru/models/chart_template.py
odoo/addons/l10n_ru/readme/CONTRIBUTORS.md
odoo/addons/l10n_ru/readme/DESCRIPTION.md
odoo/addons/l10n_ru/static/description/account.png
odoo/addons/l10n_ru/static/description/icon.png
odoo/addons/l10n_ru/static/description/index.html
odoo_addon_l10n_ru-17.0.1.0.0.16.dist-info/METADATA
odoo_addon_l10n_ru-17.0.1.0.0.16.dist-info/WHEEL
odoo_addon_l10n_ru-17.0.1.0.0.16.dist-info/top_level.txt
odoo_addon_l10n_ru-17.0.1.0.0.16.dist-info/RECORD
