Metadata-Version: 2.1
Name: odoo-addon-l10n_ru
Version: 17.0.1.0.0.16
Requires-Python: >=3.10
Requires-Dist: odoo>=17.0a,<17.1dev
Summary: Russia - Accounting
Home-page: https://github.com/OCA/l10n-russia
License: AGPL-3
Author: CodUP, Katulos, Odoo Community Association (OCA)
Author-email: support@odoo-community.org
Classifier: Programming Language :: Python
Classifier: Framework :: Odoo
Classifier: Framework :: Odoo :: 17.0
Classifier: License :: OSI Approved :: GNU Affero General Public License v3
